cc_email_templates/__init__.py
cc_email_templates/render.py
cc_email_templates/templates/__init__.py
cc_email_templates/templates/base-email-layout.html.j2
cc_email_templates/templates/base.html.j2
cc_email_templates/templates/call-to-action.html.j2
cc_email_templates/templates/simple-call-to-action.html.j2
cc_email_templates/templates/simple-call-to-action.txt.j2
cc_email_templates/templates/table-email.html.j2
cc_email_templates/templates/table-style.css
cc_email_templates/txt_processing.py
cc_email_templates-0.2.1.dist-info/LICENSE
cc_email_templates-0.2.1.dist-info/WHEEL
cc_email_templates-0.2.1.dist-info/METADATA
cc_email_templates-0.2.1.dist-info/RECORD
