Metadata-Version: 2.1
Name: cc-email-templates
Version: 0.2.1
Summary: A set of email templates used by Conflict Cartographer
Home-page: https://www.github.com/prio-data/cc_email_templates
Author: peder2911
Author-email: pglandsverk@gmail.com
Requires-Python: >=3.8,<4.0
Classifier: Programming Language :: Python :: 3
Classifier: Programming Language :: Python :: 3.10
Classifier: Programming Language :: Python :: 3.8
Classifier: Programming Language :: Python :: 3.9
Requires-Dist: Jinja2 (>=3.0.3,<4.0.0)
Requires-Dist: css-inline (>=0.8.1,<0.9.0)
